README.rst
backup.py
setup.py
utils.py
mongodb_backup.egg-info/PKG-INFO
mongodb_backup.egg-info/SOURCES.txt
mongodb_backup.egg-info/dependency_links.txt
mongodb_backup.egg-info/entry_points.txt
mongodb_backup.egg-info/requires.txt
mongodb_backup.egg-info/top_level.txt