Metadata-Version: 1.0
Name: mongodb-backup
Version: 0.1.3
Summary: A tool to backup mongodb
Home-page: http://github.com/zhangliyong/mongodb-backup
Author: Lyon Zhang
Author-email: lyzhang87@gmail.com
License: BSD
Platform: UNKNOWN
